<annotation>
  <folder>
  </folder>
  <filename>120460824_022a1c2160_flipped_jpg.rf.2f8046c41928d364c456ae0cb8609666.jpg</filename>
  <path>120460824_022a1c2160_flipped_jpg.rf.2f8046c41928d364c456ae0cb8609666.jpg</path>
  <source>
    <database>roboflow.ai</database>
  </source>
  <size>
    <width>416</width>
    <height>416</height>
    <depth>3</depth>
  </size>
  <segmented>0</segmented>
  <object>
    <name>stairs</name>
    <pose>Unspecified</pose>
    <truncated>0</truncated>
    <difficult>0</difficult>
    <occluded>0</occluded>
    <bndbox>
      <xmin>1</xmin>
      <xmax>416</xmax>
      <ymin>131</ymin>
      <ymax>411</ymax>
    </bndbox>
  </object>
</annotation>