<annotation>
  <folder>
  </folder>
  <filename>2496659788_a5aedffd30_flipped_jpg.rf.eecee3c5dc2c7e451a5a8cab2ef9d6bd.jpg</filename>
  <path>2496659788_a5aedffd30_flipped_jpg.rf.eecee3c5dc2c7e451a5a8cab2ef9d6bd.jpg</path>
  <source>
    <database>roboflow.ai</database>
  </source>
  <size>
    <width>416</width>
    <height>416</height>
    <depth>3</depth>
  </size>
  <segmented>0</segmented>
  <object>
    <name>stairs</name>
    <pose>Unspecified</pose>
    <truncated>0</truncated>
    <difficult>0</difficult>
    <occluded>0</occluded>
    <bndbox>
      <xmin>171</xmin>
      <xmax>358</xmax>
      <ymin>241</ymin>
      <ymax>416</ymax>
    </bndbox>
  </object>
</annotation>