<annotation>
	<folder></folder>
	<filename>c1_p1_140_jpg.rf.3d68f80b577031c01371144a7b6586c2.jpg</filename>
	<path>c1_p1_140_jpg.rf.3d68f80b577031c01371144a7b6586c2.jpg</path>
	<source>
		<database>roboflow.ai</database>
	</source>
	<size>
		<width>416</width>
		<height>416</height>
		<depth>3</depth>
	</size>
	<segmented>0</segmented>
	<object>
		<name>crosswalk</name>
		<pose>Unspecified</pose>
		<truncated>0</truncated>
		<difficult>0</difficult>
		<occluded>0</occluded>
		<bndbox>
			<xmin>168</xmin>
			<xmax>417</xmax>
			<ymin>6</ymin>
			<ymax>412</ymax>
		</bndbox>
	</object>
</annotation>
