<annotation>
  <folder>
  </folder>
  <filename>IMG_20181004_164709_flipped_jpg.rf.5e2a8fcb2c2b561c56e4cf94f37c2bcc.jpg</filename>
  <path>IMG_20181004_164709_flipped_jpg.rf.5e2a8fcb2c2b561c56e4cf94f37c2bcc.jpg</path>
  <source>
    <database>roboflow.ai</database>
  </source>
  <size>
    <width>416</width>
    <height>416</height>
    <depth>3</depth>
  </size>
  <segmented>0</segmented>
  <object>
    <name>stairs</name>
    <pose>Unspecified</pose>
    <truncated>0</truncated>
    <difficult>0</difficult>
    <occluded>0</occluded>
    <bndbox>
      <xmin>169</xmin>
      <xmax>293</xmax>
      <ymin>15</ymin>
      <ymax>200</ymax>
    </bndbox>
  </object>
</annotation>